{"nextStudentId": 214, "students": [{"id": 2, "name": "あさやまさなえ", "grade": "高校2年", "email": "", "courses": ["英文解釈", "英文法レベル１", "英語長文レベル１", "英検準１級", "中学2年"], "enrollDate": "2025-07", "status": "通塾", "fee": 38500, "notes": ""}, {"id": 3, "name": "嶋村ゆか", "grade": "高校1年", "email": "", "courses": ["高校2年英文法"], "enrollDate": "", "status": "通塾", "fee": 7500, "notes": ""}, {"id": 4, "name": "norikoNakayama", "grade": "中学2年", "email": "", "courses": ["英文法レベル１"], "enrollDate": "", "status": "通塾", "fee": 7500, "notes": ""}, {"id": 7, "name": "char-chan", "grade": "高校2年生", "email": "", "courses": ["英文法レベル２", "英検準１級"], "enrollDate": "", "status": "通塾", "fee": 16000, "notes": ""}, {"id": 8, "name": "下田（ひろと）準1級へ", "grade": "高校2年", "email": "", "courses": ["英検準１級"], "enrollDate": "", "status": "通塾", "fee": 8500, "notes": ""}, {"id": 9, "name": "さな", "grade": "中学3年", "email": "", "courses": ["学習管理モニター"], "enrollDate": "", "status": "通塾", "fee": 16500, "notes": ""}, {"id": 11, "name": "関根", "grade": "中学2年", "email": "", "courses": ["英検２級"], "enrollDate": "", "status": "通塾", "fee": 7500, "notes": ""}, {"id": 12, "name": "kirara", "grade": "高校1年", "email": "", "courses": ["国公立難関大学"], "enrollDate": "", "status": "通塾", "fee": 25000, "notes": ""}, {"id": 13, "name": "みむらほのか", "grade": "中学2年", "email": "", "courses": ["月曜中３英文法"], "enrollDate": "", "status": "通塾", "fee": 7500, "notes": ""}, {"id": 14, "name": "mam(ｵｸﾀﾞｸﾐｺ)", "grade": "中学2年", "email": "", "courses": ["月曜中３英文法", "英検準２級"], "enrollDate": "", "status": "通塾", "fee": 15000, "notes": ""}, {"id": 19, "name": "はる（ｲﾉｳｴﾄﾓｴ）", "grade": "中学2年", "email": "", "courses": ["月曜中３英文法"], "enrollDate": "", "status": "通塾", "fee": 7500, "notes": ""}, {"id": 21, "name": "田中恵麻", "grade": "中学2年", "email": "", "courses": ["月曜中３英文法"], "enrollDate": "", "status": "通塾", "fee": 7500, "notes": ""}, {"id": 22, "name": "アオト（弟）", "grade": "中学2年", "email": "", "courses": ["月曜中３英文法"], "enrollDate": "", "status": "通塾", "fee": 7500, "notes": ""}, {"id": 23, "name": "m-k-hotoriｷﾉｼﾀﾐｽﾞｷ", "grade": "中学2年", "email": "", "courses": ["月曜中３英文法"], "enrollDate": "", "status": "通塾", "fee": 7500, "notes": ""}, {"id": 24, "name": "ひいろ妹", "grade": "中学2年", "email": "", "courses": ["月曜中３英文法"], "enrollDate": "", "status": "通塾", "fee": 7500, "notes": ""}, {"id": 25, "name": "栗田さん妹JUNKO.K", "grade": "中学2年", "email": "", "courses": ["中学2年"], "enrollDate": "", "status": "通塾", "fee": 7500, "notes": ""}, {"id": 26, "name": "heee(ヒズメセリ)", "grade": "中学2年", "email": "", "courses": ["学習管理モニター"], "enrollDate": "", "status": "通塾", "fee": 16500, "notes": ""}, {"id": 27, "name": "ｵｵﾂｶ", "grade": "中学2年", "email": "", "courses": ["月曜中３英文法"], "enrollDate": "", "status": "通塾", "fee": 7500, "notes": ""}, {"id": 28, "name": "伊達（ﾁｮﾒｺ）", "grade": "中学2年", "email": "", "courses": ["月曜中３英文法"], "enrollDate": "", "status": "通塾", "fee": 7500, "notes": ""}, {"id": 30, "name": "prima-ao(ｶﾜｸﾞﾁｶﾖ)", "grade": "中学2年", "email": "", "courses": ["月曜中３英文法"], "enrollDate": "", "status": "通塾", "fee": 7500, "notes": ""}, {"id": 31, "name": "neight(ﾅｶｼﾏﾕﾐ)", "grade": "中学2年", "email": "", "courses": ["月曜中３英文法"], "enrollDate": "", "status": "通塾", "fee": 7500, "notes": ""}, {"id": 36, "name": "水木莉歩(ブラック)", "grade": "中学3年", "email": "", "courses": ["英文法レベル１"], "enrollDate": "", "status": "通塾", "fee": 7500, "notes": ""}, {"id": 37, "name": "郁恵（ニッタイクエ）", "grade": "中学3年", "email": "", "courses": ["英文法レベル１"], "enrollDate": "", "status": "通塾", "fee": 7500, "notes": ""}, {"id": 38, "name": "AzusaHara(ツユハラアミ)", "grade": "中学3年", "email": "", "courses": ["英文法レベル１"], "enrollDate": "", "status": "通塾", "fee": 7500, "notes": ""}, {"id": 39, "name": "大橋いつき", "grade": "中学3年", "email": "", "courses": ["英文法レベル１"], "enrollDate": "", "status": "通塾", "fee": 7500, "notes": ""}, {"id": 41, "name": "mamezuki(ﾌﾙｶﾜﾋﾛﾐ)", "grade": "中学3年", "email": "", "courses": ["英文法レベル１", "GMARCH"], "enrollDate": "", "status": "通塾", "fee": 20000, "notes": ""}, {"id": 44, "name": "大橋まお", "grade": "中学1年", "email": "", "courses": ["中学2年"], "enrollDate": "", "status": "通塾", "fee": 7500, "notes": ""}, {"id": 45, "name": "Marikohiraguri", "grade": "中学1年", "email": "", "courses": ["中学2年"], "enrollDate": "", "status": "通塾", "fee": 7500, "notes": ""}, {"id": 46, "name": "ｷﾞﾏﾉﾄﾞｶ", "grade": "中学1年", "email": "", "courses": ["中学2年"], "enrollDate": "", "status": "通塾", "fee": 7500, "notes": ""}, {"id": 47, "name": "高橋真理子", "grade": "中学1年", "email": "", "courses": ["中学2年"], "enrollDate": "", "status": "通塾", "fee": 7500, "notes": ""}, {"id": 48, "name": "イリえ", "grade": "中学1年", "email": "", "courses": ["中学2年"], "enrollDate": "", "status": "通塾", "fee": 7500, "notes": ""}, {"id": 49, "name": "yukiotsuka", "grade": "中学1年", "email": "", "courses": ["中学2年"], "enrollDate": "", "status": "通塾", "fee": 7500, "notes": ""}, {"id": 58, "name": "森下敦子", "grade": "中学1年", "email": "", "courses": ["国公立難関大学"], "enrollDate": "", "status": "通塾", "fee": 25000, "notes": ""}, {"id": 63, "name": "SatouYoko", "grade": "高校2年生", "email": "", "courses": ["GMARCH", "学習管理モニター"], "enrollDate": "", "status": "通塾", "fee": 29000, "notes": ""}, {"id": 66, "name": "ゆゆ（前山由佳）", "grade": "高校2年生", "email": "", "courses": ["学習管理モニター"], "enrollDate": "", "status": "通塾", "fee": 16500, "notes": ""}, {"id": 68, "name": "s.kan.non(金子本木)", "grade": "高校1年", "email": "", "courses": ["学習管理モニター"], "enrollDate": "", "status": "通塾", "fee": 16500, "notes": ""}, {"id": 70, "name": "naonao(上原直哉)", "grade": "中学2年", "email": "", "courses": ["学習管理モニター"], "enrollDate": "", "status": "通塾", "fee": 16500, "notes": ""}, {"id": 71, "name": "mochi-to-kinakoみむら", "grade": "高校2年生", "email": "", "courses": ["学習管理モニター"], "enrollDate": "", "status": "通塾", "fee": 16500, "notes": ""}, {"id": 75, "name": "nao(山田尚子)", "grade": "高校1年", "email": "", "courses": ["学習管理モニター"], "enrollDate": "", "status": "通塾", "fee": 16500, "notes": ""}, {"id": 77, "name": "milkcocoaみずかみなみ", "grade": "高校1年", "email": "", "courses": ["学習管理モニター"], "enrollDate": "", "status": "通塾", "fee": 16500, "notes": ""}, {"id": 78, "name": "はる（ｲﾉｳｴﾄﾓｴ）", "grade": "高校2年生", "email": "", "courses": ["高校2年英文法"], "enrollDate": "", "status": "通塾", "fee": 7500, "notes": ""}, {"id": 79, "name": "I*(ｲｼｲ)", "grade": "高校2年生", "email": "", "courses": ["国公立難関大学"], "enrollDate": "", "status": "通塾", "fee": 25000, "notes": ""}, {"id": 81, "name": "M.o(ゆいな)", "grade": "高校2年生", "email": "", "courses": ["国公立難関大学"], "enrollDate": "", "status": "通塾", "fee": 25000, "notes": ""}, {"id": 82, "name": "はなはな（ｲﾏｲﾕｳﾀﾛｳ）", "grade": "高校2年生", "email": "", "courses": ["学習管理モニター"], "enrollDate": "", "status": "通塾", "fee": 16500, "notes": ""}, {"id": 85, "name": "小枝あいな（comme.soi）", "grade": "高校2年生", "email": "", "courses": ["学習管理モニター"], "enrollDate": "", "status": "通塾", "fee": 16500, "notes": ""}, {"id": 86, "name": "よねやまけい", "grade": "高校2年生", "email": "", "courses": ["高校2年英文法"], "enrollDate": "", "status": "通塾", "fee": 7500, "notes": ""}, {"id": 90, "name": "村山(haringooo)", "grade": "高校2年生", "email": "", "courses": ["高校2年英文法"], "enrollDate": "", "status": "通塾", "fee": 7500, "notes": ""}, {"id": 91, "name": "Mai(安室ヤスムロ)", "grade": "高校2年生", "email": "", "courses": ["国公立難関大学"], "enrollDate": "", "status": "通塾", "fee": 25000, "notes": ""}, {"id": 92, "name": "Norie-kodama", "grade": "高校2年生", "email": "", "courses": ["高校2年英文法"], "enrollDate": "", "status": "通塾", "fee": 7500, "notes": ""}, {"id": 101, "name": "noriko（上村）", "grade": "高校1年", "email": "", "courses": ["高校2年英文法"], "enrollDate": "", "status": "通塾", "fee": 7500, "notes": ""}, {"id": 102, "name": "Eguchi Myuko(江口)", "grade": "高校1年", "email": "", "courses": ["高校2年英文法"], "enrollDate": "", "status": "通塾", "fee": 7500, "notes": ""}, {"id": 103, "name": "ﾅｶｼﾏﾐﾜｺ（ﾅｶｼﾏｼｮｳﾀﾛｳ）", "grade": "高校1年", "email": "", "courses": ["高校2年英文法"], "enrollDate": "", "status": "通塾", "fee": 7500, "notes": ""}, {"id": 105, "name": "alone(杉野直美)", "grade": "高校1年", "email": "", "courses": ["高校2年英文法"], "enrollDate": "", "status": "通塾", "fee": 7500, "notes": ""}, {"id": 106, "name": "Rose(カトオノサトシ)", "grade": "高校1年", "email": "", "courses": ["高校2年英文法"], "enrollDate": "", "status": "通塾", "fee": 7500, "notes": ""}, {"id": 107, "name": "かな", "grade": "高校1年", "email": "", "courses": ["学習管理モニター"], "enrollDate": "", "status": "通塾", "fee": 16500, "notes": ""}, {"id": 108, "name": "アオト", "grade": "高校1年", "email": "", "courses": ["高校2年英文法"], "enrollDate": "", "status": "通塾", "fee": 7500, "notes": ""}, {"id": 109, "name": "wrmama10(ﾓﾘｻﾜﾅﾅｴ)", "grade": "高校1年", "email": "", "courses": ["英語長文レベル１", "高校2年英文法"], "enrollDate": "", "status": "通塾", "fee": 15000, "notes": ""}, {"id": 111, "name": "ﾃﾗｵﾐﾂﾋﾛ", "grade": "高校1年", "email": "", "courses": ["高校2年英文法"], "enrollDate": "", "status": "通塾", "fee": 7500, "notes": ""}, {"id": 112, "name": "山城かおり（せいら）", "grade": "高校1年", "email": "", "courses": ["高校2年英文法"], "enrollDate": "", "status": "通塾", "fee": 7500, "notes": ""}, {"id": 113, "name": "kuwama-manami(manakwm)", "grade": "高校1年", "email": "", "courses": ["高校2年英文法"], "enrollDate": "", "status": "通塾", "fee": 7500, "notes": ""}, {"id": 114, "name": "松村リエコ", "grade": "高校1年", "email": "", "courses": ["高校2年英文法"], "enrollDate": "", "status": "通塾", "fee": 7500, "notes": ""}, {"id": 115, "name": "高田あつこ（朋樹）", "grade": "高校1年", "email": "", "courses": ["国公立難関大学"], "enrollDate": "", "status": "通塾", "fee": 25000, "notes": ""}, {"id": 116, "name": "item0710(室坂えり)", "grade": "高校1年", "email": "", "courses": ["高校2年英文法"], "enrollDate": "", "status": "通塾", "fee": 7500, "notes": ""}, {"id": 117, "name": "HiromiMitsui", "grade": "高校1年", "email": "", "courses": ["高校2年英文法"], "enrollDate": "", "status": "通塾", "fee": 7500, "notes": ""}, {"id": 118, "name": "ayako（吉田）", "grade": "高校1年", "email": "", "courses": ["高校2年英文法"], "enrollDate": "", "status": "通塾", "fee": 7500, "notes": ""}, {"id": 119, "name": "tacosakiri(根本さき)", "grade": "高校1年", "email": "", "courses": ["高校2年英文法"], "enrollDate": "", "status": "通塾", "fee": 7500, "notes": ""}, {"id": 121, "name": "菅原かおり", "grade": "高校1年", "email": "", "courses": ["国公立難関大学"], "enrollDate": "", "status": "通塾", "fee": 25000, "notes": ""}, {"id": 122, "name": "Tsutsuji", "grade": "高校1年", "email": "", "courses": ["高校2年英文法"], "enrollDate": "", "status": "通塾", "fee": 9000, "notes": ""}, {"id": 123, "name": "オガワアオト", "grade": "高校1年", "email": "", "courses": ["国公立難関大学"], "enrollDate": "", "status": "通塾", "fee": 25000, "notes": ""}, {"id": 125, "name": "室坂海來", "grade": "高校2年生", "email": "", "courses": ["国公立難関大学"], "enrollDate": "", "status": "通塾", "fee": 25000, "notes": ""}, {"id": 126, "name": "photokao", "grade": "高校1年", "email": "", "courses": ["英文法レベル１", "英語長文レベル１"], "enrollDate": "", "status": "通塾", "fee": 15000, "notes": ""}, {"id": 127, "name": "あおい（ｲｼｸﾗﾘｴｺ）", "grade": "高校2年生", "email": "", "courses": ["国公立難関大学"], "enrollDate": "", "status": "通塾", "fee": 25000, "notes": ""}, {"id": 129, "name": "早川由佳", "grade": "高校1年", "email": "", "courses": ["国公立難関大学"], "enrollDate": "", "status": "通塾", "fee": 25000, "notes": ""}, {"id": 131, "name": "マキジマレオン", "grade": "高校1年", "email": "", "courses": ["国公立難関大学"], "enrollDate": "", "status": "通塾", "fee": 25000, "notes": ""}, {"id": 133, "name": "cocotte(クボタリン)", "grade": "高校1年", "email": "", "courses": ["国公立難関大学"], "enrollDate": "", "status": "通塾", "fee": 25000, "notes": ""}, {"id": 134, "name": "hiroko（前田璃子）", "grade": "高校2年生", "email": "", "courses": ["国公立難関大学", "英検準１級"], "enrollDate": "", "status": "通塾", "fee": 33500, "notes": ""}, {"id": 135, "name": "KaoriTakano", "grade": "", "email": "", "courses": ["国公立難関大学"], "enrollDate": "", "status": "通塾", "fee": 25000, "notes": ""}, {"id": 136, "name": "ツジノノブト", "grade": "", "email": "", "courses": ["国公立難関大学"], "enrollDate": "", "status": "通塾", "fee": 25000, "notes": ""}, {"id": 137, "name": "中島そう", "grade": "", "email": "", "courses": ["国公立難関大学"], "enrollDate": "", "status": "通塾", "fee": 25000, "notes": ""}, {"id": 138, "name": "前川メイ", "grade": "", "email": "", "courses": ["学習管理モニター"], "enrollDate": "", "status": "通塾", "fee": 16500, "notes": ""}, {"id": 139, "name": "kusiroyui", "grade": "", "email": "", "courses": ["高校2年英文法"], "enrollDate": "", "status": "通塾", "fee": 7500, "notes": ""}, {"id": 140, "name": "りおな", "grade": "", "email": "", "courses": ["英文法レベル１", "英検準１級"], "enrollDate": "", "status": "通塾", "fee": 16000, "notes": ""}, {"id": 141, "name": "徳山", "grade": "", "email": "", "courses": ["英文法レベル１", "英語長文レベル１"], "enrollDate": "", "status": "通塾", "fee": 15000, "notes": ""}, {"id": 142, "name": "池田あきよ", "grade": "", "email": "", "courses": ["英文法レベル１", "英語長文レベル１"], "enrollDate": "", "status": "通塾", "fee": 15000, "notes": ""}, {"id": 143, "name": "野沢あやの", "grade": "", "email": "", "courses": ["英文法レベル１", "英語長文レベル１"], "enrollDate": "", "status": "通塾", "fee": 15000, "notes": ""}, {"id": 144, "name": "竹内もとき", "grade": "", "email": "", "courses": ["学習管理"], "enrollDate": "", "status": "通塾", "fee": 22500, "notes": ""}, {"id": 145, "name": "こやなぎみのる", "grade": "", "email": "", "courses": ["国公立難関大学"], "enrollDate": "", "status": "通塾", "fee": 25000, "notes": ""}, {"id": 146, "name": "栗原あゆみ", "grade": "", "email": "", "courses": ["英文法レベル１"], "enrollDate": "", "status": "通塾", "fee": 7500, "notes": ""}, {"id": 147, "name": "ゆきほ", "grade": "", "email": "", "courses": ["国公立難関大学"], "enrollDate": "", "status": "通塾", "fee": 25000, "notes": ""}, {"id": 200, "name": "よしだあやこ", "grade": "", "email": "", "courses": ["英文法レベル１", "英語長文レベル１"], "enrollDate": "", "status": "通塾", "fee": 15000, "notes": ""}, {"id": 201, "name": "アイザワカオリ", "grade": "", "email": "", "courses": ["中学基礎中学1年"], "enrollDate": "", "status": "通塾", "fee": 7500, "notes": ""}, {"id": 202, "name": "くらおかさき", "grade": "", "email": "", "courses": ["中学2年"], "enrollDate": "", "status": "通塾", "fee": 7500, "notes": ""}, {"id": 203, "name": "ワタナベタイガ", "grade": "", "email": "", "courses": ["英語長文レベル２"], "enrollDate": "", "status": "通塾", "fee": 9000, "notes": ""}, {"id": 204, "name": "はまだみわ", "grade": "", "email": "", "courses": ["中学2年"], "enrollDate": "", "status": "通塾", "fee": 7500, "notes": ""}, {"id": 205, "name": "ヤマザキナオコnaokoyama802", "grade": "", "email": "", "courses": ["英検準１級"], "enrollDate": "", "status": "通塾", "fee": 9850, "notes": ""}, {"id": 206, "name": "みやきまき", "grade": "", "email": "", "courses": ["月曜中３英文法", "英検準１級"], "enrollDate": "", "status": "通塾", "fee": 16000, "notes": ""}, {"id": 207, "name": "クロオカマドカ", "grade": "", "email": "", "courses": ["英検準１級"], "enrollDate": "", "status": "通塾", "fee": 8500, "notes": ""}, {"id": 208, "name": "ホタテコウタ", "grade": "", "email": "", "courses": ["国公立難関大学"], "enrollDate": "", "status": "通塾", "fee": 25000, "notes": ""}, {"id": 209, "name": "おおたじゅんこ", "grade": "", "email": "", "courses": ["英文法レベル２", "早慶クラス"], "enrollDate": "", "status": "通塾", "fee": 20000, "notes": ""}, {"id": 210, "name": "山口さくら", "grade": "", "email": "", "courses": [], "enrollDate": "", "status": "通塾", "fee": 35750, "notes": ""}, {"id": 211, "name": "なおいさちこ", "grade": "", "email": "", "courses": ["英検準１級"], "enrollDate": "", "status": "通塾", "fee": 8500, "notes": ""}, {"id": 212, "name": "なかえあやな", "grade": "", "email": "", "courses": ["英検２級"], "enrollDate": "", "status": "通塾", "fee": 8850, "notes": ""}, {"id": 213, "name": "アメミヤソウタ", "grade": "", "email": "", "courses": ["学習管理モニター"], "enrollDate": "", "status": "通塾", "fee": 16500, "notes": ""}], "courses": [{"id": 1, "name": "GMARCH", "target": "", "price": 12500, "desc": ""}, {"id": 2, "name": "中学2年", "target": "", "price": 7500, "desc": ""}, {"id": 3, "name": "中学基礎中学1年", "target": "", "price": 7500, "desc": ""}, {"id": 4, "name": "国公立難関大学", "target": "", "price": 25000, "desc": ""}, {"id": 5, "name": "学習管理", "target": "", "price": 22500, "desc": ""}, {"id": 6, "name": "学習管理モニター", "target": "", "price": 16500, "desc": ""}, {"id": 7, "name": "早慶クラス", "target": "", "price": 12500, "desc": ""}, {"id": 8, "name": "月曜中３英文法", "target": "", "price": 7500, "desc": ""}, {"id": 9, "name": "英文法レベル１", "target": "", "price": 7500, "desc": ""}, {"id": 10, "name": "英文法レベル２", "target": "", "price": 7500, "desc": ""}, {"id": 11, "name": "英文解釈", "target": "", "price": 7500, "desc": ""}, {"id": 12, "name": "英検準１級", "target": "", "price": 8500, "desc": ""}, {"id": 13, "name": "英検準２級", "target": "", "price": 7500, "desc": ""}, {"id": 14, "name": "英検２級", "target": "", "price": 7500, "desc": ""}, {"id": 15, "name": "英語長文レベル１", "target": "", "price": 7500, "desc": ""}, {"id": 16, "name": "英語長文レベル２", "target": "", "price": 7500, "desc": ""}, {"id": 17, "name": "高校2年英文法", "target": "", "price": 7500, "desc": ""}, {"id": 18, "name": "浪人生", "target": "", "price": 30000, "desc": ""}], "nextCourseId": 19, "payments": {"2025-12": {"2": {"paid": true, "date": "", "note": ""}, "3": {"paid": true, "date": "", "note": ""}, "4": {"paid": true, "date": "", "note": ""}, "7": {"paid": true, "date": "", "note": ""}, "8": {"paid": true, "date": "", "note": ""}, "9": {"paid": true, "date": "", "note": ""}, "11": {"paid": true, "date": "", "note": ""}, "12": {"paid": true, "date": "", "note": ""}, "13": {"paid": true, "date": "", "note": ""}, "14": {"paid": true, "date": "", "note": ""}, "19": {"paid": true, "date": "", "note": ""}, "21": {"paid": true, "date": "", "note": ""}, "22": {"paid": true, "date": "", "note": ""}, "23": {"paid": true, "date": "", "note": ""}, "24": {"paid": true, "date": "", "note": ""}, "25": {"paid": true, "date": "", "note": ""}, "26": {"paid": true, "date": "", "note": ""}, "27": {"paid": true, "date": "", "note": ""}, "30": {"paid": true, "date": "", "note": ""}, "36": {"paid": true, "date": "", "note": ""}, "37": {"paid": true, "date": "", "note": ""}, "38": {"paid": true, "date": "", "note": ""}, "39": {"paid": true, "date": "", "note": ""}, "41": {"paid": true, "date": "", "note": ""}, "44": {"paid": true, "date": "", "note": ""}, "45": {"paid": true, "date": "", "note": ""}, "46": {"paid": true, "date": "", "note": ""}, "47": {"paid": true, "date": "", "note": ""}, "48": {"paid": true, "date": "", "note": ""}, "49": {"paid": true, "date": "", "note": ""}, "58": {"paid": true, "date": "", "note": ""}, "63": {"paid": true, "date": "", "note": ""}, "66": {"paid": true, "date": "", "note": ""}, "68": {"paid": true, "date": "", "note": ""}, "70": {"paid": true, "date": "", "note": ""}, "71": {"paid": true, "date": "", "note": ""}, "75": {"paid": true, "date": "", "note": ""}, "77": {"paid": true, "date": "", "note": ""}, "78": {"paid": true, "date": "", "note": ""}, "79": {"paid": true, "date": "", "note": ""}, "81": {"paid": true, "date": "", "note": ""}, "82": {"paid": true, "date": "", "note": ""}, "85": {"paid": true, "date": "", "note": ""}, "86": {"paid": true, "date": "", "note": ""}, "90": {"paid": true, "date": "", "note": ""}, "91": {"paid": true, "date": "", "note": ""}, "92": {"paid": true, "date": "", "note": ""}, "101": {"paid": true, "date": "", "note": ""}, "102": {"paid": true, "date": "", "note": ""}, "103": {"paid": true, "date": "", "note": ""}, "105": {"paid": true, "date": "", "note": ""}, "106": {"paid": true, "date": "", "note": ""}, "107": {"paid": true, "date": "", "note": ""}, "108": {"paid": true, "date": "", "note": ""}, "109": {"paid": true, "date": "", "note": ""}, "111": {"paid": true, "date": "", "note": ""}, "112": {"paid": true, "date": "", "note": ""}, "113": {"paid": true, "date": "", "note": ""}, "114": {"paid": true, "date": "", "note": ""}, "115": {"paid": true, "date": "", "note": ""}, "116": {"paid": true, "date": "", "note": ""}, "117": {"paid": true, "date": "", "note": ""}, "118": {"paid": true, "date": "", "note": ""}, "119": {"paid": true, "date": "", "note": ""}, "121": {"paid": true, "date": "", "note": ""}, "122": {"paid": true, "date": "", "note": ""}, "123": {"paid": true, "date": "", "note": ""}, "125": {"paid": true, "date": "", "note": ""}, "126": {"paid": true, "date": "", "note": ""}, "127": {"paid": true, "date": "", "note": ""}, "129": {"paid": true, "date": "", "note": ""}, "131": {"paid": true, "date": "", "note": ""}, "133": {"paid": true, "date": "", "note": ""}, "134": {"paid": true, "date": "", "note": ""}, "135": {"paid": true, "date": "", "note": ""}}, "2026-01": {"2": {"paid": true, "date": "", "note": ""}, "3": {"paid": true, "date": "", "note": ""}, "4": {"paid": true, "date": "", "note": ""}, "7": {"paid": true, "date": "", "note": ""}, "8": {"paid": true, "date": "", "note": ""}, "9": {"paid": true, "date": "", "note": ""}, "11": {"paid": true, "date": "", "note": ""}, "12": {"paid": true, "date": "", "note": ""}, "14": {"paid": true, "date": "", "note": ""}, "19": {"paid": true, "date": "", "note": ""}, "21": {"paid": true, "date": "", "note": ""}, "22": {"paid": true, "date": "", "note": ""}, "23": {"paid": true, "date": "", "note": ""}, "24": {"paid": true, "date": "", "note": ""}, "26": {"paid": true, "date": "", "note": ""}, "27": {"paid": true, "date": "", "note": ""}, "30": {"paid": true, "date": "", "note": ""}, "31": {"paid": true, "date": "", "note": ""}, "36": {"paid": true, "date": "", "note": ""}, "37": {"paid": true, "date": "", "note": ""}, "39": {"paid": true, "date": "", "note": ""}, "41": {"paid": true, "date": "", "note": ""}, "44": {"paid": true, "date": "", "note": ""}, "46": {"paid": true, "date": "", "note": ""}, "47": {"paid": true, "date": "", "note": ""}, "48": {"paid": true, "date": "", "note": ""}, "49": {"paid": true, "date": "", "note": ""}, "63": {"paid": true, "date": "", "note": ""}, "66": {"paid": true, "date": "", "note": ""}, "71": {"paid": true, "date": "", "note": ""}, "75": {"paid": true, "date": "", "note": ""}, "77": {"paid": true, "date": "", "note": ""}, "78": {"paid": true, "date": "", "note": ""}, "79": {"paid": true, "date": "", "note": ""}, "81": {"paid": true, "date": "", "note": ""}, "82": {"paid": true, "date": "", "note": ""}, "85": {"paid": true, "date": "", "note": ""}, "86": {"paid": true, "date": "", "note": ""}, "91": {"paid": true, "date": "", "note": ""}, "101": {"paid": true, "date": "", "note": ""}, "103": {"paid": true, "date": "", "note": ""}, "105": {"paid": true, "date": "", "note": ""}, "108": {"paid": true, "date": "", "note": ""}, "109": {"paid": true, "date": "", "note": ""}, "111": {"paid": true, "date": "", "note": ""}, "112": {"paid": true, "date": "", "note": ""}, "113": {"paid": true, "date": "", "note": ""}, "114": {"paid": true, "date": "", "note": ""}, "115": {"paid": true, "date": "", "note": ""}, "116": {"paid": true, "date": "", "note": ""}, "118": {"paid": true, "date": "", "note": ""}, "119": {"paid": true, "date": "", "note": ""}, "121": {"paid": true, "date": "", "note": ""}, "122": {"paid": true, "date": "", "note": ""}, "125": {"paid": true, "date": "", "note": ""}, "131": {"paid": true, "date": "", "note": ""}, "136": {"paid": true, "date": "", "note": ""}, "137": {"paid": true, "date": "", "note": ""}, "138": {"paid": true, "date": "", "note": ""}, "139": {"paid": true, "date": "", "note": ""}}, "2026-02": {"2": {"paid": true, "date": "", "note": ""}, "3": {"paid": true, "date": "", "note": ""}, "4": {"paid": true, "date": "", "note": ""}, "7": {"paid": true, "date": "", "note": ""}, "8": {"paid": true, "date": "", "note": ""}, "9": {"paid": true, "date": "", "note": ""}, "11": {"paid": true, "date": "", "note": ""}, "12": {"paid": true, "date": "", "note": ""}, "14": {"paid": true, "date": "", "note": ""}, "19": {"paid": true, "date": "", "note": ""}, "21": {"paid": true, "date": "", "note": ""}, "22": {"paid": true, "date": "", "note": ""}, "23": {"paid": true, "date": "", "note": ""}, "26": {"paid": true, "date": "", "note": ""}, "27": {"paid": true, "date": "", "note": ""}, "30": {"paid": true, "date": "", "note": ""}, "31": {"paid": true, "date": "", "note": ""}, "36": {"paid": true, "date": "", "note": ""}, "37": {"paid": true, "date": "", "note": ""}, "38": {"paid": true, "date": "", "note": ""}, "39": {"paid": true, "date": "", "note": ""}, "41": {"paid": true, "date": "", "note": ""}, "44": {"paid": true, "date": "", "note": ""}, "45": {"paid": true, "date": "", "note": ""}, "46": {"paid": true, "date": "", "note": ""}, "47": {"paid": true, "date": "", "note": ""}, "48": {"paid": true, "date": "", "note": ""}, "49": {"paid": true, "date": "", "note": ""}, "58": {"paid": true, "date": "", "note": ""}, "63": {"paid": true, "date": "", "note": ""}, "66": {"paid": true, "date": "", "note": ""}, "68": {"paid": true, "date": "", "note": ""}, "70": {"paid": true, "date": "", "note": ""}, "71": {"paid": true, "date": "", "note": ""}, "75": {"paid": true, "date": "", "note": ""}, "77": {"paid": true, "date": "", "note": ""}, "78": {"paid": true, "date": "", "note": ""}, "79": {"paid": true, "date": "", "note": ""}, "81": {"paid": true, "date": "", "note": ""}, "82": {"paid": true, "date": "", "note": ""}, "85": {"paid": true, "date": "", "note": ""}, "86": {"paid": true, "date": "", "note": ""}, "91": {"paid": true, "date": "", "note": ""}, "101": {"paid": true, "date": "", "note": ""}, "102": {"paid": true, "date": "", "note": ""}, "103": {"paid": true, "date": "", "note": ""}, "105": {"paid": true, "date": "", "note": ""}, "107": {"paid": true, "date": "", "note": ""}, "108": {"paid": true, "date": "", "note": ""}, "109": {"paid": true, "date": "", "note": ""}, "111": {"paid": true, "date": "", "note": ""}, "112": {"paid": true, "date": "", "note": ""}, "113": {"paid": true, "date": "", "note": ""}, "114": {"paid": true, "date": "", "note": ""}, "115": {"paid": true, "date": "", "note": ""}, "116": {"paid": true, "date": "", "note": ""}, "117": {"paid": true, "date": "", "note": ""}, "118": {"paid": true, "date": "", "note": ""}, "119": {"paid": true, "date": "", "note": ""}, "121": {"paid": true, "date": "", "note": ""}, "122": {"paid": true, "date": "", "note": ""}, "123": {"paid": true, "date": "", "note": ""}, "125": {"paid": true, "date": "", "note": ""}, "126": {"paid": true, "date": "", "note": ""}, "127": {"paid": true, "date": "", "note": ""}, "129": {"paid": true, "date": "", "note": ""}, "131": {"paid": true, "date": "", "note": ""}, "134": {"paid": true, "date": "", "note": ""}, "136": {"paid": true, "date": "", "note": ""}, "137": {"paid": true, "date": "", "note": ""}, "138": {"paid": true, "date": "", "note": ""}, "139": {"paid": true, "date": "", "note": ""}, "140": {"paid": true, "date": "", "note": ""}, "141": {"paid": true, "date": "", "note": ""}, "142": {"paid": true, "date": "", "note": ""}, "143": {"paid": true, "date": "", "note": ""}, "144": {"paid": true, "date": "", "note": ""}, "145": {"paid": true, "date": "", "note": ""}, "146": {"paid": true, "date": "", "note": ""}, "147": {"paid": true, "date": "", "note": ""}, "200": {"paid": true, "date": "", "note": ""}, "201": {"paid": true, "date": "", "note": ""}, "202": {"paid": true, "date": "", "note": ""}, "203": {"paid": true, "date": "", "note": ""}, "204": {"paid": true, "date": "", "note": ""}, "205": {"paid": true, "date": "", "note": ""}, "206": {"paid": true, "date": "", "note": ""}, "207": {"paid": true, "date": "", "note": ""}, "208": {"paid": true, "date": "", "note": ""}, "209": {"paid": true, "date": "", "note": ""}}, "2026-04": {"2": {"paid": true, "date": "", "note": ""}, "7": {"paid": true, "date": "", "note": ""}, "8": {"paid": true, "date": "", "note": ""}, "9": {"paid": true, "date": "", "note": ""}, "11": {"paid": true, "date": "", "note": ""}, "12": {"paid": true, "date": "", "note": ""}, "13": {"paid": true, "date": "", "note": ""}, "14": {"paid": true, "date": "", "note": ""}, "19": {"paid": true, "date": "", "note": ""}, "21": {"paid": true, "date": "", "note": ""}, "22": {"paid": true, "date": "", "note": ""}, "23": {"paid": true, "date": "", "note": ""}, "26": {"paid": true, "date": "", "note": ""}, "27": {"paid": true, "date": "", "note": ""}, "30": {"paid": true, "date": "", "note": ""}, "36": {"paid": true, "date": "", "note": ""}, "37": {"paid": true, "date": "", "note": ""}, "38": {"paid": true, "date": "", "note": ""}, "39": {"paid": true, "date": "", "note": ""}, "41": {"paid": true, "date": "", "note": ""}, "44": {"paid": true, "date": "", "note": ""}, "45": {"paid": true, "date": "", "note": ""}, "46": {"paid": true, "date": "", "note": ""}, "47": {"paid": true, "date": "", "note": ""}, "48": {"paid": true, "date": "", "note": ""}, "58": {"paid": true, "date": "", "note": ""}, "63": {"paid": true, "date": "", "note": ""}, "66": {"paid": true, "date": "", "note": ""}, "68": {"paid": true, "date": "", "note": ""}, "70": {"paid": true, "date": "", "note": ""}, "71": {"paid": true, "date": "", "note": ""}, "77": {"paid": true, "date": "", "note": ""}, "78": {"paid": true, "date": "", "note": ""}, "79": {"paid": true, "date": "", "note": ""}, "81": {"paid": true, "date": "", "note": ""}, "82": {"paid": true, "date": "", "note": ""}, "85": {"paid": true, "date": "", "note": ""}, "91": {"paid": true, "date": "", "note": ""}, "101": {"paid": true, "date": "", "note": ""}, "102": {"paid": true, "date": "", "note": ""}, "103": {"paid": true, "date": "", "note": ""}, "105": {"paid": true, "date": "", "note": ""}, "106": {"paid": true, "date": "", "note": ""}, "108": {"paid": true, "date": "", "note": ""}, "109": {"paid": true, "date": "", "note": ""}, "111": {"paid": true, "date": "", "note": ""}, "112": {"paid": true, "date": "", "note": ""}, "113": {"paid": true, "date": "", "note": ""}, "114": {"paid": true, "date": "", "note": ""}, "115": {"paid": true, "date": "", "note": ""}, "116": {"paid": true, "date": "", "note": ""}, "117": {"paid": true, "date": "", "note": ""}, "118": {"paid": true, "date": "", "note": ""}, "119": {"paid": true, "date": "", "note": ""}, "121": {"paid": true, "date": "", "note": ""}, "122": {"paid": true, "date": "", "note": ""}, "123": {"paid": true, "date": "", "note": ""}, "125": {"paid": true, "date": "", "note": ""}, "127": {"paid": true, "date": "", "note": ""}, "129": {"paid": true, "date": "", "note": ""}, "131": {"paid": true, "date": "", "note": ""}, "134": {"paid": true, "date": "", "note": ""}, "136": {"paid": true, "date": "", "note": ""}, "137": {"paid": true, "date": "", "note": ""}, "138": {"paid": true, "date": "", "note": ""}, "140": {"paid": true, "date": "", "note": ""}, "142": {"paid": true, "date": "", "note": ""}, "143": {"paid": true, "date": "", "note": ""}, "145": {"paid": true, "date": "", "note": ""}, "147": {"paid": true, "date": "", "note": ""}, "200": {"paid": true, "date": "", "note": ""}, "202": {"paid": true, "date": "", "note": ""}, "203": {"paid": true, "date": "", "note": ""}, "208": {"paid": true, "date": "", "note": ""}, "211": {"paid": true, "date": "", "note": ""}, "212": {"paid": true, "date": "", "note": ""}, "213": {"paid": true, "date": "", "note": ""}}}}